CHANGES.txt
CONTRIBUTORS.txt
MANIFEST.in
README.txt
setup.cfg
setup.py
Products/__init__.py
Products.PopupCalendarWidget.egg-info/PKG-INFO
Products.PopupCalendarWidget.egg-info/SOURCES.txt
Products.PopupCalendarWidget.egg-info/dependency_links.txt
Products.PopupCalendarWidget.egg-info/entry_points.txt
Products.PopupCalendarWidget.egg-info/namespace_packages.txt
Products.PopupCalendarWidget.egg-info/not-zip-safe
Products.PopupCalendarWidget.egg-info/requires.txt
Products.PopupCalendarWidget.egg-info/top_level.txt
Products/PopupCalendarWidget/HISTORY.txt
Products/PopupCalendarWidget/LICENSE.txt
Products/PopupCalendarWidget/PopupCalendarWidget.py
Products/PopupCalendarWidget/README.txt
Products/PopupCalendarWidget/__init__.py
Products/PopupCalendarWidget/config.py
Products/PopupCalendarWidget/version.txt
Products/PopupCalendarWidget/Extensions/Install.py
Products/PopupCalendarWidget/examples/PopupCalendarType.py
Products/PopupCalendarWidget/examples/__init__.py
Products/PopupCalendarWidget/skins/popup_calendar/checkForDate.py
Products/PopupCalendarWidget/skins/popup_calendar/getCalendarDateRange.py
Products/PopupCalendarWidget/skins/popup_calendar/popup_calendar.pt
docs/HISTORY.txt
docs/INSTALL.txt
docs/LICENSE.GPL
docs/LICENSE.txt