Metadata-Version: 1.0
Name: Products.PopupCalendarWidget
Version: 1.0.6
Summary: A widget to replace the default date selector in Plone
Home-page: http://www.sixfeetup.com
Author: Six Feet Up, Inc.
Author-email: info@sixfeetup.com
License: GPL
Platform: UNKNOWN
Classifier: Framework :: Plone
Classifier: Intended Audience :: Developers
Classifier: Topic :: Software Development :: Libraries :: Python Modules
Classifier: License :: OSI Approved :: GNU General Public License (GPL)
